isitoff/__init__.py
isitoff/client.py
isitoff/isitoff.py
isitoff-0.1.0.dist-info/METADATA
isitoff-0.1.0.dist-info/WHEEL
isitoff-0.1.0.dist-info/licenses/LICENSE
isitoff-0.1.0.dist-info/RECORD
